mcp_server_kalshi/__init__.py
mcp_server_kalshi/config.py
mcp_server_kalshi/kalshi_client.py
mcp_server_kalshi/schema.py
mcp_server_kalshi/server.py
mcp_server_kalshi-0.1.3.dist-info/METADATA
mcp_server_kalshi-0.1.3.dist-info/WHEEL
mcp_server_kalshi-0.1.3.dist-info/entry_points.txt
mcp_server_kalshi-0.1.3.dist-info/top_level.txt
mcp_server_kalshi-0.1.3.dist-info/RECORD
