Metadata-Version: 2.4
Name: mcp-server-kalshi
Version: 0.1.3
Summary: An MCP server implementation for Kalshi prediction market endpoints
License: MIT
Requires-Python: >=3.10
Requires-Dist: mcp>=1.6.0
Requires-Dist: cryptography
Requires-Dist: pydantic
Requires-Dist: pydantic-settings
Provides-Extra: dev
Requires-Dist: black; extra == "dev"
